{
  "note": "由 update_etf_managers.py（GitHub Actions）自動維護的 ETF 經理人持久檔。app 讀此檔當『換手偵測』基準，跨容器重啟仍存活（取代僅存活於 /tmp 的舊機制）。請勿手動編輯。",
  "updated_at": "2026-06-23T00:13:20.656053+00:00",
  "managers": {
    "0050.TW": {
      "history": [],
      "first_seen": "2026-06-02",
      "name": "陳重銓",
      "since": null,
      "tenure_days": null,
      "last_seen": "2026-06-22"
    },
    "0051.TW": {
      "history": [
        {
          "from": "邱鉦淵",
          "to": "程惇亞",
          "detected_at": "2026-06-16",
          "since": null
        }
      ],
      "first_seen": "2026-06-16",
      "name": "程惇亞",
      "since": null,
      "tenure_days": null,
      "last_seen": "2026-06-22"
    },
    "006208.TW": {
      "history": [],
      "first_seen": "2026-06-02",
      "name": "洪珮甄",
      "since": null,
      "tenure_days": null,
      "last_seen": "2026-06-22"
    },
    "00692.TW": {
      "history": [],
      "first_seen": "2026-06-02",
      "name": "溫芳儀",
      "since": null,
      "tenure_days": null,
      "last_seen": "2026-06-22"
    },
    "00850.TW": {
      "history": [],
      "first_seen": "2026-06-02",
      "name": "邱鉦淵",
      "since": null,
      "tenure_days": null,
      "last_seen": "2026-06-22"
    },
    "0056.TW": {
      "history": [],
      "first_seen": "2026-06-02",
      "name": "陳威志",
      "since": null,
      "tenure_days": null,
      "last_seen": "2026-06-22"
    },
    "00713.TW": {
      "history": [],
      "first_seen": "2026-06-02",
      "name": "蔡宗勳",
      "since": null,
      "tenure_days": null,
      "last_seen": "2026-06-22"
    },
    "00701.TW": {
      "history": [],
      "first_seen": "2026-06-02",
      "name": "江宇騰",
      "since": null,
      "tenure_days": null,
      "last_seen": "2026-06-22"
    },
    "00878.TW": {
      "history": [],
      "first_seen": "2026-06-02",
      "name": "江宇騰",
      "since": null,
      "tenure_days": null,
      "last_seen": "2026-06-22"
    },
    "00900.TW": {
      "history": [
        {
          "from": "黃煜翔",
          "to": "洪珮甄",
          "detected_at": "2026-06-08",
          "since": null
        }
      ],
      "first_seen": "2026-06-08",
      "name": "洪珮甄",
      "since": null,
      "tenure_days": null,
      "last_seen": "2026-06-22"
    },
    "00915.TW": {
      "history": [],
      "first_seen": "2026-06-02",
      "name": "李郁馨",
      "since": null,
      "tenure_days": null,
      "last_seen": "2026-06-22"
    },
    "00918.TW": {
      "history": [],
      "first_seen": "2026-06-02",
      "name": "郭修誠",
      "since": null,
      "tenure_days": null,
      "last_seen": "2026-06-22"
    },
    "00919.TW": {
      "history": [],
      "first_seen": "2026-06-02",
      "name": "謝明志",
      "since": null,
      "tenure_days": null,
      "last_seen": "2026-06-22"
    },
    "00929.TW": {
      "history": [],
      "first_seen": "2026-06-02",
      "name": "許忠成",
      "since": null,
      "tenure_days": null,
      "last_seen": "2026-06-22"
    },
    "00936.TW": {
      "history": [],
      "first_seen": "2026-06-02",
      "name": "黃鈺民",
      "since": null,
      "tenure_days": null,
      "last_seen": "2026-06-22"
    },
    "00939.TW": {
      "history": [],
      "first_seen": "2026-06-02",
      "name": "林良一",
      "since": null,
      "tenure_days": null,
      "last_seen": "2026-06-22"
    },
    "00940.TW": {
      "history": [],
      "first_seen": "2026-06-02",
      "name": "邱鉦淵",
      "since": null,
      "tenure_days": null,
      "last_seen": "2026-06-22"
    },
    "00881.TW": {
      "history": [],
      "first_seen": "2026-06-02",
      "name": "蘇鼎宇",
      "since": null,
      "tenure_days": null,
      "last_seen": "2026-06-22"
    },
    "00891.TW": {
      "history": [],
      "first_seen": "2026-06-02",
      "name": "張圭慧",
      "since": null,
      "tenure_days": null,
      "last_seen": "2026-06-22"
    },
    "00892.TW": {
      "history": [],
      "first_seen": "2026-06-02",
      "name": "又又",
      "since": null,
      "tenure_days": null,
      "last_seen": "2026-06-22"
    },
    "00893.TW": {
      "history": [],
      "first_seen": "2026-06-02",
      "name": "游凱卉",
      "since": null,
      "tenure_days": null,
      "last_seen": "2026-06-22"
    },
    "00935.TW": {
      "history": [],
      "first_seen": "2026-06-02",
      "name": "林怡君",
      "since": null,
      "tenure_days": null,
      "last_seen": "2026-06-22"
    },
    "00679B.TW": {
      "history": [],
      "first_seen": "2026-06-02",
      "name": "周宜縉",
      "since": null,
      "tenure_days": null,
      "last_seen": "2026-06-22"
    },
    "00687B.TW": {
      "history": [],
      "first_seen": "2026-06-02",
      "name": "陳思翰",
      "since": null,
      "tenure_days": null,
      "last_seen": "2026-06-22"
    },
    "00937B.TW": {
      "history": [],
      "first_seen": "2026-06-02",
      "name": "曾盈甄",
      "since": null,
      "tenure_days": null,
      "last_seen": "2026-06-22"
    },
    "00980A.TW": {
      "history": [],
      "first_seen": "2026-06-02",
      "name": "游景德",
      "since": null,
      "tenure_days": null,
      "last_seen": "2026-06-22"
    },
    "00981A.TW": {
      "history": [],
      "first_seen": "2026-06-02",
      "name": "陳釧瑤",
      "since": null,
      "tenure_days": null,
      "last_seen": "2026-06-22"
    },
    "00982A.TW": {
      "history": [],
      "first_seen": "2026-06-02",
      "name": "陳沅易",
      "since": null,
      "tenure_days": null,
      "last_seen": "2026-06-22"
    }
  }
}
